recipe_grid/__init__.py
recipe_grid/compiler.py
recipe_grid/lint.py
recipe_grid/markdown.py
recipe_grid/number_formatting.py
recipe_grid/number_parser.py
recipe_grid/py.typed
recipe_grid/recipe.py
recipe_grid/scaled_value_string.py
recipe_grid/sphinx_ext.py
recipe_grid/units.py
recipe_grid/parser/__init__.py
recipe_grid/parser/ast.py
recipe_grid/parser/grammar.peg
recipe_grid/parser/grammar.py
recipe_grid/renderer/__init__.py
recipe_grid/renderer/html.py
recipe_grid/renderer/recipe_to_table.py
recipe_grid/renderer/table.py
recipe_grid/scripts/__init__.py
recipe_grid/scripts/recipe_grid.py
recipe_grid/scripts/recipe_grid_lint.py
recipe_grid/scripts/recipe_grid_site.py
recipe_grid/static_site/__init__.py
recipe_grid/static_site/exceptions.py
recipe_grid/static_site/href.py
recipe_grid/static_site/html_postprocessing.py
recipe_grid/static_site/recipe_directory.py
recipe_grid/static_site/standalone_page.py
recipe_grid/static_site/website.py
recipe_grid/static_site/templates/__init__.py
recipe_grid/static_site/templates/base.css
recipe_grid/static_site/templates/base.html
recipe_grid/static_site/templates/base_top_of_file.css
recipe_grid/static_site/templates/categories.html
recipe_grid/static_site/templates/homepage.html
recipe_grid/static_site/templates/normalize.css
recipe_grid/static_site/templates/recipe.html
recipe_grid/static_site/templates/recipe_tables.css
recipe_grid/static_site/templates/standalone_recipe.css
recipe_grid/static_site/templates/standalone_recipe.html
recipe_grid/static_site/templates/website.css
recipe_grid/static_site/templates/website_base.html
recipe_grid-2.1.1.dist-info/licenses/LICENSE
recipe_grid-2.1.1.dist-info/METADATA
recipe_grid-2.1.1.dist-info/WHEEL
recipe_grid-2.1.1.dist-info/entry_points.txt
recipe_grid-2.1.1.dist-info/top_level.txt
recipe_grid-2.1.1.dist-info/RECORD
