Metadata-Version: 2.4
Name: recipe_grid
Version: 2.1.1
Summary: A tool for generating table-based recipe descriptions.
Author-email: Jonathan Heathcote <mail@jhnet.co.uk>
Project-URL: source, https://github.com/mossblaser/recipe_grid
License-File: LICENSE
Requires-Dist: lxml
Requires-Dist: marko~=2.0.0
Requires-Dist: peggie
Requires-Dist: jinja2
Dynamic: license-file
